footsteps/__init__.py
footsteps-0.1.9.dist-info/LICENSE
footsteps-0.1.9.dist-info/METADATA
footsteps-0.1.9.dist-info/WHEEL
footsteps-0.1.9.dist-info/top_level.txt
footsteps-0.1.9.dist-info/RECORD
