Metadata-Version: 2.1
Name: footsteps
Version: 0.1.9
Summary: a minimal experiment logging package
Home-page: https://github.com/HastingsGreer/footsteps
Author: Hastings Greer
Author-email: footsteps@hgreer.com
Project-URL: Bug Tracker, https://github.com/HastingsGreer/footsteps/issues
Classifier: Programming Language :: Python :: 3
Classifier: License :: OSI Approved :: MIT License
Classifier: Operating System :: POSIX :: Linux
Requires-Python: >=3.7
License-File: LICENSE
